{
  "name": "Elgyem",
  "jname": "\u30ea\u30b0\u30ec\u30fc",
  "jtranslit": "Rigur\u0113",
  "tmname": "Ligray",
  "category": "Cerebral",
  "typebox": "1",
  "type1": "Psychic",
  "abilityn": "d",
  "ability1": "Telepathy",
  "ability2": "Synchronize",
  "abilityd": "Analytic",
  "ndex": 605.0,
  "height-ftin": "1'08\"",
  "height-m": 0.5,
  "weight-lbs": 19.8,
  "weight-kg": 9.0,
  "egggroupn": "1",
  "egggroup1": "Human-Like",
  "eggcycles": 20.0,
  "expyield": 67.0,
  "lv100exp": 1000000.0,
  "evtotal": 1.0,
  "evsa": 1.0,
  "gendercode": "127",
  "color": "Blue",
  "catchrate": 255.0,
  "body": "06",
  "pokefordex": "elgyem",
  "generation": 5.0,
  "friendship": 70.0,
  "type_efficacy": {
    "Normal": 100.0,
    "Flying": 100.0,
    "Fighting": 50.0,
    "Ground": 100.0,
    "Rock": 100.0,
    "Bug": 200.0,
    "Poison": 100.0,
    "Ghost": 200.0,
    "Steel": 100.0,
    "Fire": 100.0,
    "Grass": 100.0,
    "Electric": 100.0,
    "Psychic": 50.0,
    "Water": 100.0,
    "Ice": 100.0,
    "Dragon": 100.0,
    "Dark": 200.0,
    "Fairy": 100.0
  }
}