{
  "encounters": {
    "3": [
      "Tentacool",
      "Wingull",
      "Pelipper",
      "Magikarp",
      "Wailmer",
      "Luvdisc",
      "Corsola"
    ],
    "oras": [
      "Tentacool",
      "Tentacruel",
      "Pelipper",
      "Magikarp",
      "Wailmer",
      "Luvdisc",
      "Corsola"
    ]
  },
  "name": "Ever Grande City",
  "jpname": "\u30b5\u30a4\u30e6\u30a6\u30b7\u30c6\u30a3",
  "jptrans": "Saiyu City",
  "image": "Ever Grande City ORAS.png",
  "imageIII": "Ever Grande City RS.png",
  "slogan": "The paradise of flowers, the sea, and Pok\u00e9mon.",
  "mapdesc": "This city is blanketed in a profusion of colorful blooms. It plays host to the grand Pok\u00e9mon League.",
  "region": "Hoenn",
  "north": "Victory Road (Hoenn)",
  "northalt": "Victory Road",
  "west": "Route 128",
  "regionwest": "Hoenn",
  "league": "Hoenn",
  "leaguetitle": "[[Pok\u00e9mon Ruby and Sapphire Versions|{{color|000|RS}}]]/[[Pok\u00e9mon Omega Ruby and Alpha Sapphire|{{color|000|ORAS}}]]",
  "elite1": "Sidney",
  "elite1type": "Dark",
  "elite1sprite": "VSSidney.png",
  "elite2": "Phoebe",
  "elite2type": "Ghost",
  "elite2sprite": "VSPhoebe.png",
  "elite3": "Glacia",
  "elite3type": "Ice",
  "elite3sprite": "VSGlacia.png",
  "elite4": "Drake",
  "elite4type": "Dragon",
  "elite4sprite": "VSDrake.png",
  "champion": "Steven",
  "championlink": "Steven Stone",
  "championtype": "Steel",
  "championsprite": "VSSteven.png{{!}}100px",
  "leaguetitle2": "[[Pok\u00e9mon Emerald Version|{{color|000|E}}]]",
  "elite12": "Sidney",
  "elite1type2": "Dark",
  "elite1sprite2": "Spr RS Sidney.png",
  "elite22": "Phoebe",
  "elite2type2": "Ghost",
  "elite2sprite2": "Spr RS Phoebe.png",
  "elite32": "Glacia",
  "elite3type2": "Ice",
  "elite3sprite2": "Spr RS Glacia.png",
  "elite42": "Drake",
  "elite4type2": "Dragon",
  "elite4sprite2": "Spr RS Drake.png",
  "champion2": "Wallace",
  "championtype2": "Water",
  "championsprite2": "Spr E Wallace.png",
  "colordark": "CD853F",
  "colormed": "EE9A49",
  "colorlight": "FFA54F",
  "generation": "3"
}