{
  "encounters": {
    "2": [
      "Pidgey",
      "Rattata",
      "Jigglypuff",
      "Abra",
      "Drowzee",
      "Ditto",
      "Hoothoot",
      "Snubbull",
      "Tentacool",
      "Tentacruel",
      "Krabby",
      "Magikarp",
      "Staryu",
      "Corsola",
      "Kingler",
      "Caterpie",
      "Metapod",
      "Butterfree",
      "Weedle",
      "Kakuna",
      "Beedrill",
      "Exeggcute",
      "Ledyba",
      "Spinarak",
      "Pineco",
      "Pichu",
      "Cleffa",
      "Igglybuff",
      "Tyrogue",
      "Smoochum",
      "Elekid",
      "Magby"
    ],
    "hs": [
      "Rattata",
      "Abra",
      "Drowzee",
      "Ditto",
      "Tentacool",
      "Tentacruel",
      "Krabby",
      "Magikarp",
      "Staryu",
      "Corsola",
      "Kingler",
      "Exeggcute",
      "Hoothoot",
      "Pineco",
      "Ledyba",
      "Spinarak",
      "Ralts",
      "Linoone",
      "Whismur",
      "Bidoof",
      "Buizel"
    ]
  },
  "number": "34",
  "size": "250",
  "image": "Johto Route 34 HGSS.png",
  "imageII": "Johto Route 34 GSC.png",
  "type": "land",
  "north": "Goldenrod City",
  "south": "Ilex Forest",
  "region": "Johto",
  "surf": "yes",
  "generation": "2",
  "mapdesc": "A lush, green path, even though it's right next to a city."
}