{
  "name": "Lapras",
  "jname": "\u30e9\u30d7\u30e9\u30b9",
  "jtranslit": "Rapurasu",
  "tmname": "Laplace",
  "forme": "2",
  "form2": "Gigantamax Lapras",
  "image2": "0131Lapras-Gigantamax.png",
  "ndex": 131.0,
  "type1": "Water",
  "type2": "Ice",
  "category": "Transport",
  "height-ftin": "8'02\"",
  "height-m": 2.5,
  "height-ftin2": "78'09\"+",
  "height-m2": "24.0+",
  "weight-lbs": 485.0,
  "weight-kg": 220.0,
  "weight-lbs2": "???",
  "weight-kg2": "???",
  "ability1": "Water Absorb",
  "ability2": "Shell Armor",
  "abilityd": "Hydration",
  "egggroupn": "2",
  "egggroup1": "Monster",
  "egggroup2": "Water 1",
  "eggcycles": 40.0,
  "evtotal": 2.0,
  "evhp": 2.0,
  "expyield": 187.0,
  "oldexp": 219.0,
  "lv100exp": 1250000.0,
  "gendercode": "127",
  "color": "Blue",
  "catchrate": 45.0,
  "body": "03",
  "pokefordex": "lapras",
  "generation": 1.0,
  "friendship": 70.0,
  "type_efficacy": {
    "Normal": 100.0,
    "Fighting": 200.0,
    "Flying": 100.0,
    "Poison": 100.0,
    "Ground": 100.0,
    "Rock": 200.0,
    "Bug": 100.0,
    "Ghost": 100.0,
    "Steel": 100.0,
    "Fire": 100.0,
    "Water": 50.0,
    "Grass": 200.0,
    "Electric": 200.0,
    "Psychic": 100.0,
    "Ice": 25.0,
    "Dragon": 100.0,
    "Dark": 100.0,
    "Fairy": 100.0
  }
}